salesforce_mcp_server/__init__.py
salesforce_mcp_server/__main__.py
salesforce_mcp_server/_version.py
salesforce_mcp_server/errors.py
salesforce_mcp_server/logging_config.py
salesforce_mcp_server/server.py
salesforce_mcp_server/oauth/__init__.py
salesforce_mcp_server/oauth/storage.py
salesforce_mcp_server/oauth/token_access.py
salesforce_mcp_server/oauth/token_verifier.py
salesforce_mcp_server/salesforce/__init__.py
salesforce_mcp_server/salesforce/client_manager.py
salesforce_mcp_server/salesforce/operations.py
salesforce_mcp_server/tools/__init__.py
salesforce_mcp_server/tools/bulk.py
salesforce_mcp_server/tools/metadata.py
salesforce_mcp_server/tools/query.py
salesforce_mcp_server/tools/records.py
salesforce_mcp_server-0.4.2.dist-info/METADATA
salesforce_mcp_server-0.4.2.dist-info/WHEEL
salesforce_mcp_server-0.4.2.dist-info/entry_points.txt
salesforce_mcp_server-0.4.2.dist-info/licenses/LICENSE
salesforce_mcp_server-0.4.2.dist-info/RECORD
