Metadata-Version: 2.4
Name: salesforce-mcp-server
Version: 0.4.2
Summary: Salesforce MCP Server with multi-user OAuth PKCE support for AI agents
License-File: LICENSE
Keywords: ai-agent,api,claude,crm,llm,mcp,model-context-protocol,oauth,pkce,salesforce
Classifier: Development Status :: 3 - Alpha
Classifier: Intended Audience :: Developers
Classifier: License :: OSI Approved :: MIT License
Classifier: Programming Language :: Python :: 3
Classifier: Programming Language :: Python :: 3.14
Classifier: Topic :: Software Development :: Libraries :: Python Modules
Requires-Python: >=3.14
Requires-Dist: aiofiles>=25.1.0
Requires-Dist: cryptography>=46.0.4
Requires-Dist: fastmcp>=2.14.4
Requires-Dist: httpx>=0.28.1
Requires-Dist: mcp>=1.26.0
Requires-Dist: msgspec>=0.20.0
Requires-Dist: py-key-value-aio[redis]>=0.3.0
Requires-Dist: python-dotenv>=1.2.1
Requires-Dist: simple-salesforce>=1.12.9
Requires-Dist: typer>=0.21.1
